django_diagram/__init__.py
django_diagram/__main__.py
django_diagram/app.py
django_diagram/mermaid.py
test/__init__.py
test/test_app.py
test/test_mermaid.py
django_diagram-0.0.1.dist-info/LICENSE
django_diagram-0.0.1.dist-info/METADATA
django_diagram-0.0.1.dist-info/WHEEL
django_diagram-0.0.1.dist-info/top_level.txt
django_diagram-0.0.1.dist-info/RECORD
