Metadata-Version: 2.1
Name: django-diagram
Version: 0.0.1
Summary: Generate an Entity Relationship Diagram for a Django project in Mermaid format
Home-page: https://github.com/nick-solly/django-diagram.git
Author: Nick Solly
Author-email: nick@sudofox.co
License: All Rights Reserved
Classifier: Environment :: Web Environment
Classifier: Intended Audience :: Developers
Classifier: Operating System :: OS Independent
Classifier: Programming Language :: Python
Classifier: Programming Language :: Python :: 3
Classifier: Programming Language :: Python :: 3 :: Only
Classifier: Programming Language :: Python :: 3.6
Classifier: Programming Language :: Python :: 3.7
Classifier: Programming Language :: Python :: 3.8
Classifier: Topic :: Internet :: WWW/HTTP
Classifier: Topic :: Internet :: WWW/HTTP :: Dynamic Content
Classifier: Framework :: Django
License-File: LICENSE
